README.md
setup.py
dnevnikmos/__init__.py
dnevnikmos/errors.py
dnevnikmos/homeworks.py
dnevnikmos/lessons.py
dnevnikmos/marks.py
dnevnikmos/school.py
dnevnikmos/user.py
dnevnikmos/user_token_getter.py
dnevnikmos.egg-info/PKG-INFO
dnevnikmos.egg-info/SOURCES.txt
dnevnikmos.egg-info/dependency_links.txt
dnevnikmos.egg-info/top_level.txt